Metadata-Version: 2.1
Name: django-cache-middleware
Version: 0.0.1
Summary: A Django app for the caching api data while get method and removing after data altered or created.
Home-page: https://github.com/rjnp2/django-cache-middleware
Author: rjnp2
Author-email: rjnp2@outlook.com
License: MIT License
Platform: UNKNOWN
Classifier: Environment :: Web Environment
Classifier: Framework :: Django
Classifier: Intended Audience :: Developers
Classifier: License :: OSI Approved :: MIT License
Classifier: Operating System :: OS Independent
Classifier: Programming Language :: Python
Classifier: Programming Language :: Python :: 3.10
Classifier: Topic :: Internet :: WWW/HTTP
Classifier: Topic :: Internet :: WWW/HTTP :: Dynamic Content
Requires-Python: >=3.8
Provides-Extra: dev
Requires-Dist: twine (>=4.0.2) ; extra == 'dev'
